template_supersuper
