Metadata-Version: 1.0
Name: django-template-supersuper
Version: 0.1.1
Summary: Adds "super_super" method to block nodes in Django templates.
Home-page: https://github.com/frnhr/django-template-supersuper
Author: Fran Hrzenjak
Author-email: fran@changeset.hr
License: MIT
Platform: UNKNOWN
